gh_issue_exporter/__init__.py
gh_issue_exporter/cli.py
gh_issue_exporter/exporter.py
gh_issue_exporter/gh_utils.py
gh_issue_exporter/importer.py
gh_issue_exporter-0.0.2.dist-info/METADATA
gh_issue_exporter-0.0.2.dist-info/WHEEL
gh_issue_exporter-0.0.2.dist-info/entry_points.txt
gh_issue_exporter-0.0.2.dist-info/top_level.txt
gh_issue_exporter-0.0.2.dist-info/RECORD
