Metadata-Version: 2.1
Name: gh-issue-exporter
Version: 0.0.2
Summary: Easy way to export github issues
Author: Joakim Loxdal
Author-email: loxdal@proton.me
Project-URL: Repository, https://github.com/mrkickling/github-issue-exporter.git
Requires-Python: >=3.8
Requires-Dist: requests ~=2.0
Provides-Extra: dev
Requires-Dist: pytest ; extra == 'dev'
